Metadata-Version: 2.1
Name: pprobs
Version: 0.0.4
Summary: a library for probability computation
Home-page: UNKNOWN
Author: Mohamadreza Kariminejad
Author-email: mokar2001@gmail.com
License: MIT
Keywords: calculator
Platform: UNKNOWN
Classifier: Development Status :: 5 - Production/Stable
Classifier: Intended Audience :: Education
Classifier: Operating System :: Microsoft :: Windows :: Windows 10
Classifier: License :: OSI Approved :: MIT License
Classifier: Programming Language :: Python :: 3
License-File: LICENCE.txt
